<?xml version="1.0" encoding="utf-8" ?>
<dwsync>
<file name="icon-xls.svg" server="vps70258.inmotionhosting.com/soleburystrat.com/" local="133359819210000000" remote="133359819210000000" Dst="2" />
<file name="icon-video.png" server="vps70258.inmotionhosting.com/soleburystrat.com/" local="133359819210000000" remote="133359819210000000" Dst="2" />
<file name="icon-audio.png" server="vps70258.inmotionhosting.com/soleburystrat.com/" local="133359819210000000" remote="133359819210000000" Dst="2" />
<file name="icon-word.png" server="vps70258.inmotionhosting.com/soleburystrat.com/" local="133359819210000000" remote="133359819210000000" Dst="2" />
<file name="icon-xbrl.png" server="vps70258.inmotionhosting.com/soleburystrat.com/" local="133359819210000000" remote="133359819210000000" Dst="2" />
<file name="icon-html.png" server="vps70258.inmotionhosting.com/soleburystrat.com/" local="133359819210000000" remote="133359819210000000" Dst="2" />
<file name="icon-xbrl.svg" server="vps70258.inmotionhosting.com/soleburystrat.com/" local="133359819210000000" remote="133359819210000000" Dst="2" />
<file name="icon-pdf.png" server="vps70258.inmotionhosting.com/soleburystrat.com/" local="133359819210000000" remote="133359819210000000" Dst="2" />
<file name="icon-webinar.svg" server="vps70258.inmotionhosting.com/soleburystrat.com/" local="133359819210000000" remote="133359819210000000" Dst="2" />
<file name="icon-word.svg" server="vps70258.inmotionhosting.com/soleburystrat.com/" local="133359819210000000" remote="133359819210000000" Dst="2" />
<file name="icon-html.svg" server="vps70258.inmotionhosting.com/soleburystrat.com/" local="133359819210000000" remote="133359819210000000" Dst="2" />
<file name="icon-video.svg" server="vps70258.inmotionhosting.com/soleburystrat.com/" local="133359819210000000" remote="133359819210000000" Dst="2" />
<file name="icon-pdf.svg" server="vps70258.inmotionhosting.com/soleburystrat.com/" local="133359819210000000" remote="133359819210000000" Dst="2" />
<file name="icon-webinar.png" server="vps70258.inmotionhosting.com/soleburystrat.com/" local="133359819210000000" remote="133359819210000000" Dst="2" />
<file name="icon-xls.png" server="vps70258.inmotionhosting.com/soleburystrat.com/" local="133359819210000000" remote="133359819210000000" Dst="2" />
<file name="icon-audio.svg" server="vps70258.inmotionhosting.com/soleburystrat.com/" local="133359819210000000" remote="133359819210000000" Dst="2" />
</dwsync>